fourth_dimension
