Metadata-Version: 2.1
Name: fdfdtest
Version: 1.4
Summary: Yantu tools for python
Home-page: https://gitee.com/hustai/Fourth-Dimension
Author: yantu-tech
Author-email: GuoHuai Wu <wu466687121@qq.com>
License: MIT License
Keywords: python,yantu,中文
Classifier: Intended Audience :: Developers
Classifier: Programming Language :: Python :: 3
Requires-Python: >=3.8
